salvajson/__init__.py
salvajson/__main__.py
salvajson/_version.py
salvajson/salvajson.js
salvajson/salvajson.py
salvajson-2.7.5.dist-info/METADATA
salvajson-2.7.5.dist-info/WHEEL
salvajson-2.7.5.dist-info/licenses/AUTHORS.md
salvajson-2.7.5.dist-info/licenses/LICENSE
salvajson-2.7.5.dist-info/RECORD
