Metadata-Version: 2.4
Name: salvajson
Version: 2.7.5
Summary: Fix corrupted JSON files using the jsonic JSON parser in JavaScript
Author-email: Adam Twardoch <adam+github@twardoch.com>
License-Expression: Apache-2.0
License-File: AUTHORS.md
License-File: LICENSE
Classifier: Development Status :: 4 - Beta
Classifier: Intended Audience :: Developers
Classifier: License :: OSI Approved :: Apache Software License
Classifier: Programming Language :: Python :: 3
Classifier: Programming Language :: Python :: 3.10
Classifier: Programming Language :: Python :: 3.11
Classifier: Programming Language :: Python :: 3.12
Classifier: Topic :: Software Development :: Libraries :: Python Modules
Requires-Python: >=3.10
Requires-Dist: fire>=0.7.0
Requires-Dist: orjson>=3.10
Requires-Dist: pythonmonkey>=1.1.0
Provides-Extra: dev
Requires-Dist: build>=1.0.0; extra == 'dev'
Requires-Dist: hatchling>=1.18.0; extra == 'dev'
Requires-Dist: python-semantic-release>=8.7.0; extra == 'dev'
Requires-Dist: twine>=4.0.0; extra == 'dev'
Provides-Extra: test
Requires-Dist: coverage>=6.0.0; extra == 'test'
Requires-Dist: pytest-cov>=4.0.0; extra == 'test'
Requires-Dist: pytest-sugar>=1.0.0; extra == 'test'
Requires-Dist: pytest-timeout>=2.3.0; extra == 'test'
Requires-Dist: pytest-xdist>=3.6.0; extra == 'test'
Requires-Dist: pytest>=7.0.0; extra == 'test'
